pynsett/__init__.py
pynsett/__main__.py
pynsett/auxiliary/__init__.py
pynsett/auxiliary/collator.py
pynsett/auxiliary/line_finder.py
pynsett/auxiliary/names_modifier.py
pynsett/auxiliary/prior_knowedge.py
pynsett/auxiliary/random.py
pynsett/auxiliary/rule_utils.py
pynsett/auxiliary/tags.py
pynsett/auxiliary/transform.py
pynsett/data/feminine_names.txt
pynsett/data/masculine_names.txt
pynsett/data/profile.txt
pynsett/discourse/__init__.py
pynsett/discourse/anaphora.py
pynsett/discourse/discourse.py
pynsett/discourse/global_graph_visitors.py
pynsett/discourse/paragraphs.py
pynsett/discourse/single_tokens_visitors.py
pynsett/drt/__init__.py
pynsett/drt/drs.py
pynsett/drt/drs_matcher.py
pynsett/drt/drs_rule.py
pynsett/drt/node_matcher.py
pynsett/examples/__init__.py
pynsett/examples/discourse_example.py
pynsett/examples/extract_from_text.py
pynsett/examples/extract_from_wikipedia.py
pynsett/examples/extract_written_by.py
pynsett/examples/multiple_match_example.py
pynsett/examples/negation.py
pynsett/examples/sentence_creation.py
pynsett/examples/start_server.py
pynsett/extractor/__init__.py
pynsett/inference/__init__.py
pynsett/inference/forward_inference.py
pynsett/install/__init__.py
pynsett/knowledge/__init__.py
pynsett/knowledge/drs_ner_cleaner.py
pynsett/metric/__init__.py
pynsett/nl/__init__.py
pynsett/rules/adjectives.parvus
pynsett/rules/delete.parvus
pynsett/rules/generic_relations.rules
pynsett/rules/names.parvus
pynsett/rules/recruitment_relations.rules
pynsett/rules/subordinates.parvus
pynsett/rules/test.rules
pynsett/rules/todo.txt
pynsett/rules/verbs.parvus
pynsett/rules/wikidata.rules
pynsett/rules/parsing/adjectives.parvus
pynsett/rules/parsing/compound1.parvus
pynsett/rules/parsing/compound2.parvus
pynsett/rules/parsing/delete.parvus
pynsett/rules/parsing/inter_sentence_anaphora.parvus
pynsett/rules/parsing/intra_sentence_anaphora.parvus
pynsett/rules/parsing/names.parvus
pynsett/rules/parsing/prepositions.parvus
pynsett-0.1.8.dist-info/METADATA
pynsett-0.1.8.dist-info/WHEEL
pynsett-0.1.8.dist-info/top_level.txt
pynsett-0.1.8.dist-info/RECORD
