Metadata-Version: 2.1
Name: pynsett
Version: 0.1.8
Summary: A programmable relation extractor
Home-page: http://github.com/fractalego/pynsett
Author: Alberto Cetoli
Author-email: alberto@nlulite.com
License: UNKNOWN
Platform: UNKNOWN
Classifier: License :: OSI Approved :: MIT License
Requires-Dist: spacy (==2.1.3)
Requires-Dist: nltk (==3.2.1)
Requires-Dist: rdflib (==4.2.2)
Requires-Dist: yappi (==1.0)
Requires-Dist: gensim (==3.7.2)
Requires-Dist: parvusdb (==0.0.26)
Requires-Dist: nose (==1.3.7)
Requires-Dist: allennlp (==0.8.3)
Requires-Dist: flask (==1.0.2)
Requires-Dist: flask-cors
